{
  "lesson1":
    {
      "name": "Английский язык A2",
      "start_time": "11.40",
      "finish_time": "13.10",
      "type": "Практика",
      "teacher_name": "Федорова Екатерина Сергеевна",
      "room_number": "3211",
      "address": "ул.Ломоносова д.9 лит. Е"
    }
  ,
  "lesson2":
    {
      "name": "Английский язык A2",
      "start_time": "13.30",
      "finish_time": "15.00",
      "type": "Практика",
      "teacher_name": "Федорова Екатерина Сергеевна",
      "room_number": "3211",
      "address": "ул.Ломоносова д.9 лит. Е"
    }
}
